LICENSE
LICENSE.txt
README.rst
setup.cfg
setup.py
nitasthecat/__init__.py
nitasthecat/nitas.py
nitasthecat.egg-info/PKG-INFO
nitasthecat.egg-info/SOURCES.txt
nitasthecat.egg-info/dependency_links.txt
nitasthecat.egg-info/top_level.txt